{
  "version-11.x/docs": {
    "Release Notes": ["version-11.x/releases/release-notes", "version-11.x/releases/migrate"],
    "Getting Started": [
      "version-11.x/introduction",
      "version-11.x/installation",
      "version-11.x/quickstart",
      "version-11.x/updating",
      "version-11.x/troubleshoot"
    ],
    "Main Concepts": [
      "version-11.x/main/overview",
      "version-11.x/main/content",
      "version-11.x/main/dialog",
      "version-11.x/main/code",
      "version-11.x/main/memory",
      "version-11.x/main/module",
      "version-11.x/main/nlu",
      "version-11.x/main/emulator"
    ],
    "Advanced Guides": [
      "version-11.x/advanced/debug",
      "version-11.x/advanced/configuration",
      "version-11.x/advanced/authentication",
      "version-11.x/advanced/i18n",
      "version-11.x/advanced/custom-module",
      "version-11.x/advanced/analytics",
      "version-11.x/advanced/architecture",
      "version-11.x/advanced/performances",
      "version-11.x/advanced/hosting",
      "version-11.x/advanced/versions",
      "version-11.x/advanced/pipelines",
      "version-11.x/advanced/cluster",
      "version-11.x/advanced/monitoring"
    ],
    "Channels": [
      "version-11.x/channels/web",
      "version-11.x/channels/messenger",
      "version-11.x/channels/telegram",
      "version-11.x/channels/converse",
      "version-11.x/channels/faq"
    ],
    "Tutorials": [
      "version-11.x/tutorials/proactive",
      "version-11.x/tutorials/skill-slot",
      "version-11.x/tutorials/skill-call-api",
      "version-11.x/tutorials/external-api",
      "version-11.x/tutorials/shortlinks",
      "version-11.x/tutorials/existing-backend",
      "version-11.x/tutorials/database",
      "version-11.x/tutorials/timeouts",
      "version-11.x/tutorials/hitl",
      "version-11.x/tutorials/jump-to",
      "version-11.x/tutorials/interbot",
      "version-11.x/tutorials/contextual-faq",
      "version-11.x/tutorials/chat-3rd-party-OAuth",
      "version-11.x/tutorials/listen-file-changes"
    ],
    "Pro Edition": ["version-11.x/pro/about-pro", "version-11.x/pro/licensing", "version-11.x/pro/rbac"]
  }
}
